{
  "scene": "尴尬",
  "description": "当别人因为情境不适、犯错、被关注或不知道如何反应时，会表现出的尴尬行为",
  "sub_scenes": [
    {
      "type": "轻度尴尬",
      "patterns": ["哈哈…", "呃…", "有点不好意思", "我刚刚说错了吗"],
      "simple_explanation": "对方只是稍微不确定或不自然。",
      "why": "他们可能不确定自己是否说对话、是否合适。",
      "suggestion_steps": [
        "轻松回应：\"没关系啦\"。",
        "换个话题减少对方压力。",
        "让氛围变轻松，例如笑一下。",
        "避免继续放大尴尬的点。"
      ],
      "emotion_level": "低",
      "context_notes": "常见于小失误、轻微社交错误"
    },
    {
      "type": "明显尴尬",
      "patterns": ["呃…我不是那个意思", "我应该闭嘴的…", "抱歉我好像说错话了", "我不知道该说什么"],
      "simple_explanation": "对方感觉不安且希望修正局面。",
      "why": "他们觉得自己的表达影响他人或造成困扰。",
      "suggestion_steps": [
        "告诉对方：\"没关系，我明白你的意思。\"",
        "避免重复他们说错的话。",
        "温和转移话题。",
        "不要嘲笑或取笑对方的尴尬。"
      ],
      "emotion_level": "中",
      "context_notes": "可能伴随脸红、紧张笑"
    },
    {
      "type": "社交场合的不知所措",
      "patterns": ["我应该说点什么吗？", "我不太知道怎么回应", "你们继续就好…", "我去一下厕所"],
      "simple_explanation": "对方不知道如何加入对话或感到自己格格不入。",
      "why": "他们可能不熟悉话题、害羞或缺乏安全感。",
      "suggestion_steps": [
        "主动介绍他们参与话题，例如：\"你觉得呢？\"",
        "不要强迫他们一直说话。",
        "如果他们退出对话，尊重其意愿。",
        "给予简单、能让他们接得住的问题。"
      ],
      "emotion_level": "中",
      "context_notes": "适合温和引导，不要给压力"
    }
  ],
  "general_principles": [
    "尴尬是一种常见的社交情绪。",
    "不要嘲笑或模仿对方的尴尬反应。",
    "轻松、自然的回应能减少尴尬感。",
    "改变话题比深挖错误更有效。",
    "让对方感觉安全、不被评判。"
  ],
  "nonverbal_signals": [
    { "signal": "摸脸或摸脖子", "meaning": "紧张、不自然" },
    { "signal": "尴尬笑", "meaning": "用笑来缓解压力" },
    { "signal": "目光躲避", "meaning": "不想让别人注意到他们的失误" }
  ]
}
